MANIFEST.in
NEW_FUNCTIONALITIES.md
README.md
contributors.md
requirements.txt
setup.cfg
setup.py
setup.sh
jarviscli/.gitignore
jarviscli/CmdInterpreter.py
jarviscli/Jarvis.py
jarviscli/__init__.py
jarviscli/__main__.py
jarviscli.egg-info/PKG-INFO
jarviscli.egg-info/SOURCES.txt
jarviscli.egg-info/dependency_links.txt
jarviscli.egg-info/requires.txt
jarviscli.egg-info/top_level.txt
jarviscli/packages/__init__.py
jarviscli/packages/audioHandler.py
jarviscli/packages/chat.py
jarviscli/packages/chuck.py
jarviscli/packages/directions_to.py
jarviscli/packages/evaluator.py
jarviscli/packages/fileHandler.py
jarviscli/packages/forecast.py
jarviscli/packages/mapps.py
jarviscli/packages/music.py
jarviscli/packages/near_me.py
jarviscli/packages/news.py
jarviscli/packages/picshow.py
jarviscli/packages/record.py
jarviscli/packages/reminder.py
jarviscli/packages/shutdown.py
jarviscli/packages/systemOptions.py
jarviscli/packages/timeIn.py
jarviscli/packages/todo.py
jarviscli/packages/umbrella.py
jarviscli/packages/weatherIn.py
jarviscli/packages/weather_pinpoint.py
jarviscli/packages/aiml/.gitignore
jarviscli/packages/aiml/__init__.py
jarviscli/packages/aiml/brain.py
jarviscli/packages/aiml/chat.aiml
jarviscli/packages/aiml/default.aiml
jarviscli/packages/aiml/emotion.aiml
jarviscli/packages/aiml/std-startup.xml
jarviscli/packages/memory/.gitignore
jarviscli/packages/memory/__init__.py
jarviscli/packages/memory/memory.py
jarviscli/tests/__init__.py
jarviscli/tests/test_brain.py
jarviscli/tests/test_default.py
jarviscli/tests/test_evaluator.py
jarviscli/tests/test_forecast.py
jarviscli/tests/test_help.py
jarviscli/tests/test_memory.py
jarviscli/tests/test_music.py
jarviscli/tests/test_near_me.py
jarviscli/tests/test_news.py
jarviscli/tests/test_parser.py
jarviscli/tests/test_timeIn.py
jarviscli/tests/test_weatherIn.py
jarviscli/utilities/GeneralUtilities.py
jarviscli/utilities/__init__.py
jarviscli/utilities/dateTime.py
jarviscli/utilities/lexicalSimilarity.py
jarviscli/utilities/textParser.py
jarviscli/utilities/voice.py